biofaker/__init__.py
biofaker/biofaker.py
biofaker/cli.py
biofaker-0.1.2.dist-info/AUTHORS.rst
biofaker-0.1.2.dist-info/LICENSE
biofaker-0.1.2.dist-info/METADATA
biofaker-0.1.2.dist-info/WHEEL
biofaker-0.1.2.dist-info/entry_points.txt
biofaker-0.1.2.dist-info/top_level.txt
biofaker-0.1.2.dist-info/RECORD
