Metadata-Version: 2.1
Name: biofaker
Version: 0.1.2
Summary: A Python package that generates fake biodata.
Home-page: https://github.com/robertopreste/biofaker
Author: Roberto Preste
Author-email: robertopreste@gmail.com
License: MIT license
Keywords: biofaker
Platform: UNKNOWN
Classifier: Development Status :: 2 - Pre-Alpha
Classifier: Intended Audience :: Developers
Classifier: License :: OSI Approved :: MIT License
Classifier: Natural Language :: English
Classifier: Programming Language :: Python :: 3
Classifier: Programming Language :: Python :: 3.6
Classifier: Programming Language :: Python :: 3.7
Requires-Dist: Click (>=7.0)
